duck-0.1.dist-info/DESCRIPTION.rst
duck-0.1.dist-info/metadata.json
duck-0.1.dist-info/METADATA
duck-0.1.dist-info/RECORD
duck-0.1.dist-info/top_level.txt
duck-0.1.dist-info/WHEEL
ducktype/__init__.py
ducktype/entities.py
duck-0.1.data/scripts/ducktype
