Metadata-Version: 2.0
Name: duck
Version: 0.1
Summary: Parse Ducktype files and convert them to Mallard.
Home-page: UNKNOWN
Author: Shaun McCance
Author-email: shaunm@gnome.org
License: MIT
Platform: UNKNOWN
Classifier: Development Status :: 3 - Alpha
Classifier: Environment :: Console
Classifier: Intended Audience :: Customer Service
Classifier: Intended Audience :: Developers
Classifier: Intended Audience :: Other Audience
Classifier: Intended Audience :: System Administrators
Classifier: Programming Language :: Python :: 3
Classifier: Programming Language :: Python :: 3 :: Only
Classifier: Topic :: Documentation
Classifier: Topic :: Software Development :: Documentation
Classifier: Topic :: Text Processing :: Markup
Classifier: Topic :: Text Processing :: Markup :: XML
Classifier: License :: OSI Approved :: MIT License
